odoo/addons/web_widget_json_graph/README.rst
odoo/addons/web_widget_json_graph/__init__.py
odoo/addons/web_widget_json_graph/__manifest__.py
odoo/addons/web_widget_json_graph/i18n/web_widget_json_graph.pot
odoo/addons/web_widget_json_graph/readme/CONTRIBUTORS.rst
odoo/addons/web_widget_json_graph/readme/CREDITS.rst
odoo/addons/web_widget_json_graph/readme/DESCRIPTION.rst
odoo/addons/web_widget_json_graph/readme/ROADMAP.rst
odoo/addons/web_widget_json_graph/readme/USAGE.rst
odoo/addons/web_widget_json_graph/static/description/icon.png
odoo/addons/web_widget_json_graph/static/description/index.html
odoo/addons/web_widget_json_graph/static/description/widget_in_action.png
odoo/addons/web_widget_json_graph/static/src/js/web_widget_json_graph.js
odoo/addons/web_widget_json_graph/static/src/xml/web_widget_json_graph.xml
odoo_addon_web_widget_json_graph-15.0.1.0.0.3.dist-info/METADATA
odoo_addon_web_widget_json_graph-15.0.1.0.0.3.dist-info/WHEEL
odoo_addon_web_widget_json_graph-15.0.1.0.0.3.dist-info/top_level.txt
odoo_addon_web_widget_json_graph-15.0.1.0.0.3.dist-info/RECORD
